odoo/addons/l10n_br_nfse_ginfes/README.rst
odoo/addons/l10n_br_nfse_ginfes/__init__.py
odoo/addons/l10n_br_nfse_ginfes/__manifest__.py
odoo/addons/l10n_br_nfse_ginfes/constants/ginfes.py
odoo/addons/l10n_br_nfse_ginfes/i18n/l10n_br_nfse_ginfes.pot
odoo/addons/l10n_br_nfse_ginfes/i18n/pt_BR.po
odoo/addons/l10n_br_nfse_ginfes/models/__init__.py
odoo/addons/l10n_br_nfse_ginfes/models/document.py
odoo/addons/l10n_br_nfse_ginfes/models/res_company.py
odoo/addons/l10n_br_nfse_ginfes/readme/CONFIGURE.rst
odoo/addons/l10n_br_nfse_ginfes/readme/CONTRIBUTORS.rst
odoo/addons/l10n_br_nfse_ginfes/readme/DESCRIPTION.rst
odoo/addons/l10n_br_nfse_ginfes/readme/INSTALL.rst
odoo/addons/l10n_br_nfse_ginfes/readme/ROADMAP.rst
odoo/addons/l10n_br_nfse_ginfes/readme/USAGE.rst
odoo/addons/l10n_br_nfse_ginfes/static/description/icon.png
odoo/addons/l10n_br_nfse_ginfes/static/description/index.html
odoo/addons/l10n_br_nfse_ginfes/static/src/img/itajuba.png
odoo/addons/l10n_br_nfse_ginfes/tests/__init__.py
odoo/addons/l10n_br_nfse_ginfes/tests/test_fiscal_document_nfse_ginfes.py
odoo/addons/l10n_br_nfse_ginfes/tests/nfse/001_50_nfse.xml
odoo12_addon_l10n_br_nfse_ginfes-12.0.3.0.0.dist-info/METADATA
odoo12_addon_l10n_br_nfse_ginfes-12.0.3.0.0.dist-info/WHEEL
odoo12_addon_l10n_br_nfse_ginfes-12.0.3.0.0.dist-info/top_level.txt
odoo12_addon_l10n_br_nfse_ginfes-12.0.3.0.0.dist-info/RECORD
