Metadata-Version: 2.1
Name: odoo12-addon-l10n-br-nfse-ginfes
Version: 12.0.3.0.0
Summary: NFS-e (Ginfes)
Home-page: https://github.com/OCA/l10n-brazil
Author: KMEE, Odoo Community Association (OCA)
Author-email: support@odoo-community.org
License: AGPL-3
Platform: UNKNOWN
Classifier: Programming Language :: Python
Classifier: Framework :: Odoo
Classifier: License :: OSI Approved :: GNU Affero General Public License v3
Classifier: Development Status :: 4 - Beta
Requires-Python: >=3.5
Requires-Dist: erpbrasil.assinatura
Requires-Dist: erpbrasil.base
Requires-Dist: erpbrasil.edoc
Requires-Dist: erpbrasil.transmissao
Requires-Dist: nfselib.ginfes
Requires-Dist: odoo12-addon-l10n-br-nfse
Requires-Dist: odoo (<12.1dev,>=12.0a)
